{
  "categories": [
    "cabinetry",
    "coach",
    "hobby",
    "job",
    "milling"
  ],
  "photos": [
    {
      "category": "cabinetry",
      "src": "assets/images/gallery/cabinetry/cover.jpg",
      "filename": "cover.jpg",
      "order": 1
    },
    {
      "category": "cabinetry",
      "src": "assets/images/gallery/cabinetry/IMG_1121.jpg",
      "filename": "IMG_1121.jpg",
      "order": 2
    },
    {
      "category": "cabinetry",
      "src": "assets/images/gallery/cabinetry/IMG_1122.jpg",
      "filename": "IMG_1122.jpg",
      "order": 3
    },
    {
      "category": "cabinetry",
      "src": "assets/images/gallery/cabinetry/IMG_1123.jpg",
      "filename": "IMG_1123.jpg",
      "order": 4
    },
    {
      "category": "cabinetry",
      "src": "assets/images/gallery/cabinetry/IMG_1125.jpg",
      "filename": "IMG_1125.jpg",
      "order": 5
    },
    {
      "category": "cabinetry",
      "src": "assets/images/gallery/cabinetry/IMG_1126.jpg",
      "filename": "IMG_1126.jpg",
      "order": 6
    },
    {
      "category": "cabinetry",
      "src": "assets/images/gallery/cabinetry/IMG_1127.jpg",
      "filename": "IMG_1127.jpg",
      "order": 7
    },
    {
      "category": "cabinetry",
      "src": "assets/images/gallery/cabinetry/IMG_1751.JPG",
      "filename": "IMG_1751.JPG",
      "order": 9
    },
    {
      "category": "cabinetry",
      "src": "assets/images/gallery/cabinetry/IMG_1753.JPG",
      "filename": "IMG_1753.JPG",
      "order": 10
    },
    {
      "category": "cabinetry",
      "src": "assets/images/gallery/cabinetry/IMG_3084.jpg",
      "filename": "IMG_3084.jpg",
      "order": 11
    },
    {
      "category": "cabinetry",
      "src": "assets/images/gallery/cabinetry/IMG_3086.jpg",
      "filename": "IMG_3086.jpg",
      "order": 12
    },
    {
      "category": "cabinetry",
      "src": "assets/images/gallery/cabinetry/IMG_3089.jpg",
      "filename": "IMG_3089.jpg",
      "order": 13
    },
    {
      "category": "cabinetry",
      "src": "assets/images/gallery/cabinetry/IMG_3301.jpg",
      "filename": "IMG_3301.jpg",
      "order": 14
    },
    {
      "category": "cabinetry",
      "src": "assets/images/gallery/cabinetry/IMG_3302.jpg",
      "filename": "IMG_3302.jpg",
      "order": 15
    },
    {
      "category": "cabinetry",
      "src": "assets/images/gallery/cabinetry/IMG_3836.jpg",
      "filename": "IMG_3836.jpg",
      "order": 8
    },
    {
      "category": "cabinetry",
      "src": "assets/images/gallery/cabinetry/IMG_E1743.JPG",
      "filename": "IMG_E1743.JPG",
      "order": 16
    },
    {
      "category": "cabinetry",
      "src": "assets/images/gallery/cabinetry/wine-rack-pegs.jpg",
      "filename": "wine-rack-pegs.jpg",
      "order": 17
    },
    {
      "category": "coach",
      "src": "assets/images/gallery/coach/cover.jpg",
      "filename": "cover.jpg",
      "order": 1
    },
    {
      "category": "hobby",
      "src": "assets/images/gallery/hobby/cover.jpg",
      "filename": "cover.jpg",
      "order": 1
    },
    {
      "category": "hobby",
      "src": "assets/images/gallery/hobby/IMG_0401.JPG",
      "filename": "IMG_0401.JPG",
      "order": 2
    },
    {
      "category": "hobby",
      "src": "assets/images/gallery/hobby/IMG_0561.JPG",
      "filename": "IMG_0561.JPG",
      "order": 3
    },
    {
      "category": "hobby",
      "src": "assets/images/gallery/hobby/IMG_1493.JPG",
      "filename": "IMG_1493.JPG",
      "order": 4
    },
    {
      "category": "hobby",
      "src": "assets/images/gallery/hobby/IMG_1496.JPG",
      "filename": "IMG_1496.JPG",
      "order": 5
    },
    {
      "category": "hobby",
      "src": "assets/images/gallery/hobby/IMG_1503.JPG",
      "filename": "IMG_1503.JPG",
      "order": 6
    },
    {
      "category": "hobby",
      "src": "assets/images/gallery/hobby/IMG_1645.JPG",
      "filename": "IMG_1645.JPG",
      "order": 7
    },
    {
      "category": "hobby",
      "src": "assets/images/gallery/hobby/IMG_2186.JPG",
      "filename": "IMG_2186.JPG",
      "order": 8
    },
    {
      "category": "job",
      "src": "assets/images/gallery/job/cover.jpg",
      "filename": "cover.jpg",
      "order": 1
    },
    {
      "category": "job",
      "src": "assets/images/gallery/job/IMG_0088.JPG",
      "filename": "IMG_0088.JPG",
      "order": 2
    },
    {
      "category": "job",
      "src": "assets/images/gallery/job/IMG_0420.JPG",
      "filename": "IMG_0420.JPG",
      "order": 3
    },
    {
      "category": "job",
      "src": "assets/images/gallery/job/IMG_0746.JPG",
      "filename": "IMG_0746.JPG",
      "order": 4
    },
    {
      "category": "job",
      "src": "assets/images/gallery/job/IMG_0885.JPG",
      "filename": "IMG_0885.JPG",
      "order": 5
    },
    {
      "category": "job",
      "src": "assets/images/gallery/job/IMG_0898.jpg",
      "filename": "IMG_0898.jpg",
      "order": 6
    },
    {
      "category": "job",
      "src": "assets/images/gallery/job/IMG_0905.JPG",
      "filename": "IMG_0905.JPG",
      "order": 7
    },
    {
      "category": "job",
      "src": "assets/images/gallery/job/IMG_1001.JPG",
      "filename": "IMG_1001.JPG",
      "order": 8
    },
    {
      "category": "job",
      "src": "assets/images/gallery/job/IMG_1744.JPG",
      "filename": "IMG_1744.JPG",
      "order": 9
    },
    {
      "category": "job",
      "src": "assets/images/gallery/job/IMG_2770.jpg",
      "filename": "IMG_2770.jpg",
      "order": 10
    },
    {
      "category": "job",
      "src": "assets/images/gallery/job/IMG_3298.jpg",
      "filename": "IMG_3298.jpg",
      "order": 11
    },
    {
      "category": "job",
      "src": "assets/images/gallery/job/IMG_3299.jpg",
      "filename": "IMG_3299.jpg",
      "order": 12
    },
    {
      "category": "job",
      "src": "assets/images/gallery/job/IMG_4026.jpg",
      "filename": "IMG_4026.jpg",
      "order": 13
    },
    {
      "category": "job",
      "src": "assets/images/gallery/job/KKJJ1130.JPG",
      "filename": "KKJJ1130.JPG",
      "order": 14
    },
    {
      "category": "job",
      "src": "assets/images/gallery/job/LRUK2040.JPG",
      "filename": "LRUK2040.JPG",
      "order": 15
    },
    {
      "category": "milling",
      "src": "assets/images/gallery/milling/Corbel Custom Milling.jpg",
      "filename": "Corbel Custom Milling.jpg",
      "order": 2
    },
    {
      "category": "milling",
      "src": "assets/images/gallery/milling/cover.jpg",
      "filename": "cover.jpg",
      "order": 1
    },
    {
      "category": "milling",
      "src": "assets/images/gallery/milling/IMG_3916.jpg",
      "filename": "IMG_3916.jpg",
      "order": 3
    },
    {
      "category": "milling",
      "src": "assets/images/gallery/milling/IMG_4043.jpg",
      "filename": "IMG_4043.jpg",
      "order": 4
    },
    {
      "category": "milling",
      "src": "assets/images/gallery/milling/IMG_4051.jpg",
      "filename": "IMG_4051.jpg",
      "order": 5
    },
    {
      "category": "milling",
      "src": "assets/images/gallery/milling/IMG_E0937.JPG",
      "filename": "IMG_E0937.JPG",
      "order": 6
    },
    {
      "category": "milling",
      "src": "assets/images/gallery/milling/locking chevron-close up.jpg",
      "filename": "locking chevron-close up.jpg",
      "order": 7
    },
    {
      "category": "milling",
      "src": "assets/images/gallery/milling/Samurai Carving.jpg",
      "filename": "Samurai Carving.jpg",
      "order": 8
    },
    {
      "category": "milling",
      "src": "assets/images/gallery/milling/VDQZ6300.JPG",
      "filename": "VDQZ6300.JPG",
      "order": 9
    }
  ]
}
